{
  "rows": [
    {
      "id": "8526144221",
      "txnCode":"1234567",
      "accountNO":"10010103",
      "scenarioName":"A公司为C公司提供劳务,借：库存现金／银行存款13510,贷：主营业务收入 13510",
      "bank":"010000 156 1001010302 000001",
      "direction": "D-DEBIT",
      "moneyType": "CNY",
      "accountType":"1001010301",
      "amount":  "201125",
      "remark":""
    },{
      "id": "85260121",
      "txnCode":"1234567",
      "accountNO":"10010103",
      "scenarioName":"A公司为C公司提供劳务,借：库存现金／银行存款13510,贷：主营业务收入 13510",
      "bank":"010000 156 1001010302 000001",
      "direction": "D-DEBIT",
      "moneyType": "CNY",
      "accountType":"1001010301",
      "amount":  "201145",
      "remark":""
    },{
      "id": "852604321",
      "txnCode":"1234567",
      "accountNO":"10010103",
      "scenarioName":"A公司为C公司提供劳务,借：库存现金／银行存款13510,贷：主营业务收入 13510",
      "bank":"010000 156 1001010302 000001",
      "direction": "D-DEBIT",
      "moneyType": "CNY",
      "accountType":"1001010301",
      "amount":  "2550145",
      "remark":""
    },{
      "id": "8526044221",
      "txnCode":"1234567",
      "accountNO":"10010103",
      "scenarioName":"A公司为C公司提供劳务,借：库存现金／银行存款13510,贷：主营业务收入 13510",
      "bank":"010000 156 1001010302 000001",
      "direction": "D-DEBIT",
      "moneyType": "CNY",
      "accountType":"1001010301",
      "amount":  "205",
      "remark":""
    }
  ]
}
