{
  "rows": [
    {
      "id": "8526044221",
      "accountingDay": "12",
      "voucherNo": "143234131243123",
      "orderNo": "1243234123",
      "processingBatchNo":  "134131323113",
      "logNo":  "14323",
      "system":  "2345245243",
      "txnCode":  "1253354325456",
      "txnCode1":  "1253354325456",
      "txnDate":  "2019-04-21",
      "txnTm":  "15:12:12",
      "txnBank":  "423432435423",
      "txnAccount":  "23452435234523",
      "txnUser":  "423432435423",
      "terminalNo":  "243523452",
      "channelNo":  "423432435423",
      "correctFlg":  "冲正",
      "oriTxnDate":  "2019-04-21",
      "oriSummonsNo":  "134332454642",
      "onlineUpdateFlag":  "联机生成",
      "txnType":  "1",
      "是否手工传票标志":  "手工入账",
      "creditedNo":  "2143124323",
      "date1":  "2019-04-21",
      "systemNo1":  "24324524352345243",
      "sysKey":  "134123412",
      "type":  "134123412",
      "no1":  "2134",
      "subjectNo":  "234523452435",
      "currency":  "12",
      "isCredit":  "借方",
      "money":  "1324",
      "date2":  "2019-04-21",
      "fileType":  "1",
      "productType":  "123",
      "no3":  "1213414323",
      "no4":  "12134123144323",
      "type2":  "214312",
      "mainNo":  "3456346",
      "mainNo":  "3456346",
      "type4":  "4",
      "type5":  "1",
      "no5":  "1234124321",
      "mianNo2":  "1431243421412",
      "no8":  "14124312",
      "no9":  "14124312",
      "redType":  "红字",
      "no10":  "432423545",
      "no11":  "1454362456",
      "type11":  "12",
      "type12":  "4234",
      "type13":  "4234",
      "type13":  "134",
      "type14":  "343678665",
      "type15":  "209-03-08",
      "type16":  "28",
      "type17":  "28",
      "type18":  "786",
      "type19":  "786",
      "type20":  "2352435",
      "type21":  "134",
      "type22":  "134",
      "type23":  "lihong",
      "type24":  "98765432",
      "type25":  "54321347898765432",
      "type26":  "外币",
      "type27":  "12345",
      "type28":  "12%",
      "date11":  "2019-05-06",
      "no21":  "635243213456",
      "no22":  "2134567890",
      "no23":  "21345678",
      "no25":  "21345678",
      "no27":  "7654321",
      "updTm":  "2019-03-09",
      "time":  "2019-03-09"
    },{
      "id": "8526044222",
      "accountingDay": "65432",
      "voucherNo": "45239876543567865432",
      "orderNo": "567987y654324567",
      "processingBatchNo":  "54345876543256768",
      "logNo":  "253876543567",
      "system":  "2345245243",
      "txnCode":  "1253354325456",
      "txnCode1":  "1253354325456",
      "txnDate":  "2019-04-21",
      "txnTm":  "15:12:12",
      "txnBank":  "423432435423",
      "txnAccount":  "23452435234523",
      "txnUser":  "423432435423",
      "terminalNo":  "243523452",
      "channelNo":  "423432435423",
      "correctFlg":  "冲正",
      "oriTxnDate":  "2019-04-21",
      "oriSummonsNo":  "134332454642",
      "onlineUpdateFlag":  "联机生成",
      "txnType":  "1",
      "isManualSubpoena":  "手工入账",
      "creditedNo":  "2143124323",
      "date1":  "2019-04-21",
      "systemNo1":  "24324524352345243",
      "sysKey":  "134123412",
      "type":  "134123412",
      "no1":  "2134",
      "subjectNo":  "234523452435",
      "currency":  "12",
      "isCredit":  "借方",
      "money":  "1324",
      "date2":  "2019-04-21",
      "fileType":  "1",
      "productType":  "123",
      "no3":  "1213414323",
      "no4":  "12134123144323",
      "type2":  "214312",
      "mainNo":  "3456346",
      "type4":  "4",
      "type5":  "1",
      "no5":  "1234124321",
      "mianNo2":  "1431243421412",
      "no8":  "14124312",
      "no9":  "14124312",
      "redType":  "红字",
      "no10":  "432423545",
      "no11":  "1454362456",
      "type11":  "12",
      "type12":  "4234",
      "type33":  "4234",
      "type13":  "134",
      "type14":  "343678665",
      "type15":  "209-03-08",
      "type16":  "28",
      "type17":  "28",
      "type18":  "786",
      "type19":  "786",
      "type20":  "2352435",
      "type21":  "134",
      "type22":  "134",
      "type23":  "ad",
      "type24":  "98765432",
      "type25":  "54321347898765432",
      "type26":  "外币",
      "type27":  "12345",
      "type28":  "12%",
      "date11":  "2019-05-06",
      "no21":  "635243213456",
      "no22":  "2134567890",
      "no23":  "21345678",
      "no25":  "21345678",
      "no27":  "7654321",
      "updTm":  "2019-03-09",
      "time":  "2019-03-09"
    }
  ]
}